{"metadata":{"usedHelpers":[],"marked":[],"modules":{"imports":[],"exports":{"exported":[],"specifiers":[]}}},"options":{"filename":"/imports/data/resolvers.js","filenameRelative":"/imports/data/resolvers.js","env":{},"retainLines":false,"highlightCode":true,"suppressDeprecationMessages":false,"presets":[],"plugins":[[[],null],[[],null],[[],null],[[],null],[[],null],[[],null],[[],null],[[],{"polyfill":false}],[[],null],[[],null],[[],null],[[],null],[[],null],[[],null],[[],null],[[],null],[[],{"loose":true}],[[],{"loose":true}],[[],null],[[],{"loose":true}],[[],null],[[],null],[[],{"allowTopLevelThis":true,"strict":false,"loose":true}],[[],null],[[],null],[[],null],[[],null],[[],null],[[],{"loose":true}],[[],null],[[],null],[[],null],[[],null],[[],null],[[],null],[[],null],[[],null]],"ignore":[],"code":true,"metadata":true,"ast":false,"comments":true,"compact":false,"minified":false,"sourceMap":true,"sourceMaps":true,"sourceMapTarget":"/imports/data/resolvers.js.map","sourceFileName":"/imports/data/resolvers.js","babelrc":false,"sourceType":"module","moduleIds":false,"passPerPreset":false,"basename":"resolvers"},"ignored":false,"code":"exports.__esModule = true;\nvar resolvers = {};\n\nexports[\"default\"] = resolvers;","ast":null,"map":{"version":3,"sources":["/imports/data/resolvers.js"],"names":[],"mappings":";AAAA,IAAM,YAAY,EAAZ;;qBAIS","file":"/imports/data/resolvers.js.map","sourcesContent":["const resolvers = {\n\n};\n\nexport default resolvers;"]},"hash":"6ead8b6431775adde63f14360a1f7299de820ff9"}
